pyconfigurathon/__init__.py
pyconfigurathon/configurator.py
pyconfigurathon-0.1.2.dist-info/LICENSE
pyconfigurathon-0.1.2.dist-info/WHEEL
pyconfigurathon-0.1.2.dist-info/METADATA
pyconfigurathon-0.1.2.dist-info/RECORD
